app_template/__init__.py
app_template/app_template.py
app_config_template-0.2.2.dist-info/METADATA
app_config_template-0.2.2.dist-info/WHEEL
app_config_template-0.2.2.dist-info/RECORD
