Metadata-Version: 2.1
Name: app-config-template
Version: 0.2.2
Summary: Configs and logs wrapper
Author: Vladimir Muzychenko
Author-email: vladimir.muzychenko@gmail.com
Requires-Python: >=3.11,<4.0
Classifier: Programming Language :: Python :: 3
Classifier: Programming Language :: Python :: 3.11
